TOP-SoC/sandbox/SoC-32bit/testbench_dram2/lpddr4_dummy.v
module lpddr4_dummy (
    input wire clk,
    input wire cs,
    input wire we,
    input wire ras,
    input wire cas,
    input wire [13:0] addr,  // Ini adalah byte address dari AXI
    input wire [2:0] ba,
    inout wire [31:0] dq,
    input wire [3:0] dm,
    input wire dqs
);

    // Memory array - perbesar untuk cover address range yang dibutuhkan
    reg [31:0] memory [0:4095]; // 16KB memory (4096 words)
    reg [31:0] data_out;
    reg output_enable;
    
    // PERBAIKAN: Konversi byte address ke word address
    // addr adalah byte address, kita perlu word address
    wire [11:0] word_addr = addr[13:2];  // Byte address dibagi 4 (shift right 2 bits)
    wire [11:0] mem_addr = (word_addr < 4096) ? word_addr : 12'h000; // Bounds check
    
    assign dq = output_enable ? data_out : 32'hZ;
    
    // Initialize memory from hex file
    initial begin
        $readmemh("test_program.hex", memory);
        data_out = 32'h0;
        output_enable = 1'b0;
        
        // Debug: Show loaded program
        $display("LPDDR4: Memory initialized, showing first few instructions:");
        $display("  Word[0x000] = 0x%08x (byte addr 0x0000)", memory[0]);
        $display("  Word[0x001] = 0x%08x (byte addr 0x0004)", memory[1]);
        $display("  Word[0x002] = 0x%08x (byte addr 0x0008)", memory[2]);
        $display("  Word[0x400] = 0x%08x (byte addr 0x1000)", memory[1024]);
    end
    
    // Memory operations
    always @(posedge clk) begin
        if (!cs && !ras && !cas) begin
            if (!we) begin
                // Write operation
                if (word_addr < 4096) begin
                    memory[mem_addr] <= dq;
                    // $display("LPDDR4: Write - byte_addr=0x%04x, word_addr=0x%03x, data=0x%08x", 
                            // addr, mem_addr, dq);
                end else begin
                    // $display("LPDDR4: Write OUT OF BOUNDS - byte_addr=0x%04x, word_addr=0x%03x", 
                            // addr, word_addr);
                end
                output_enable <= 1'b0;
            end else begin
                // Read operation
                if (word_addr < 4096) begin
                    data_out <= memory[mem_addr];
                    output_enable <= 1'b1;
                    // $display("LPDDR4: Read - byte_addr=0x%04x, word_addr=0x%03x, data=0x%08x", 
                            // addr, mem_addr, memory[mem_addr]);
                end else begin
                    data_out <= 32'hDEADBEEF;
                    output_enable <= 1'b1;
                    $display("LPDDR4: Read OUT OF BOUNDS - byte_addr=0x%04x, word_addr=0x%03x, returning DEADBEEF", 
                            addr, word_addr);
                end
            end
        end else begin
            output_enable <= 1'b0;
        end
    end

endmodule

TOP-SoC/sandbox/SoC-32bit/testbench_dram/dram_controller.v
module dram_controller #(
    parameter AXI4_ID_WIDTH = 4,
    parameter ADDR_WIDTH = 32,
    parameter DATA_WIDTH = 32
)(
    input wire clk,
    input wire rst_n,
    
    // AXI4 Interface
    // Write Address Channel
    input  wire [AXI4_ID_WIDTH-1:0] M2_AXI4_AWID,
    input  wire [ADDR_WIDTH-1:0]    M2_AXI4_AWADDR,
    input  wire [7:0]               M2_AXI4_AWLEN,
    input  wire [2:0]               M2_AXI4_AWSIZE,
    input  wire [1:0]               M2_AXI4_AWBURST,
    input  wire                     M2_AXI4_AWVALID,
    output reg                      M2_AXI4_AWREADY,
    // Write Data Channel
    input  wire [DATA_WIDTH-1:0]    M2_AXI4_WDATA,
    input  wire [(DATA_WIDTH/8)-1:0] M2_AXI4_WSTRB,
    input  wire                     M2_AXI4_WLAST,
    input  wire                     M2_AXI4_WVALID,
    output reg                      M2_AXI4_WREADY,
    // Write Response Channel
    output reg  [AXI4_ID_WIDTH-1:0] M2_AXI4_BID,
    output reg  [1:0]               M2_AXI4_BRESP,
    output reg                      M2_AXI4_BVALID,
    input  wire                     M2_AXI4_BREADY,
    // Read Address Channel
    input  wire [AXI4_ID_WIDTH-1:0] M2_AXI4_ARID,
    input  wire [ADDR_WIDTH-1:0]    M2_AXI4_ARADDR,
    input  wire [7:0]               M2_AXI4_ARLEN,
    input  wire [2:0]               M2_AXI4_ARSIZE,
    input  wire [1:0]               M2_AXI4_ARBURST,
    input  wire                     M2_AXI4_ARVALID,
    output reg                      M2_AXI4_ARREADY,
    // Read Data Channel
    output reg  [AXI4_ID_WIDTH-1:0] M2_AXI4_RID,
    output reg  [DATA_WIDTH-1:0]    M2_AXI4_RDATA,
    output reg  [1:0]               M2_AXI4_RRESP,
    output reg                      M2_AXI4_RLAST,
    output reg                      M2_AXI4_RVALID,
    input  wire                     M2_AXI4_RREADY,
    
    // LPDDR4 Interface
    output reg                      dram_ck,
    output reg                      dram_cs,
    output reg                      dram_we,
    output reg                      dram_ras,
    output reg                      dram_cas,
    output reg  [13:0]              dram_addr,
    output reg  [2:0]               dram_ba,
    inout  wire [31:0]              dram_dq,
    output reg  [3:0]               dram_dm,
    output reg                      dram_dqs
);

    // Internal registers
    reg [AXI4_ID_WIDTH-1:0] write_id;
    reg [AXI4_ID_WIDTH-1:0] read_id;
    reg [ADDR_WIDTH-1:0] write_addr;
    reg [ADDR_WIDTH-1:0] read_addr;
    reg [7:0] write_len;
    reg [7:0] read_len;
    reg [7:0] write_count;
    reg [7:0] read_count;
    
    // State machine parameters
    localparam IDLE = 2'b00;
    localparam ADDR_PHASE = 2'b01;
    localparam DATA_PHASE = 2'b10;
    localparam RESP_PHASE = 2'b11;
    
    reg [1:0] write_state;
    reg [1:0] read_state;
    
    reg [DATA_WIDTH-1:0] dram_data_out;
    reg dram_data_oe;
    reg [DATA_WIDTH-1:0] read_data_reg;
    reg read_data_valid;
    
    assign dram_dq = dram_data_oe ? dram_data_out : 32'hZ;
    
    // Write channel state machine
    always @(posedge clk or negedge rst_n) begin
        if (!rst_n) begin
            write_state <= IDLE;
            M2_AXI4_AWREADY <= 1'b0;
            M2_AXI4_WREADY <= 1'b0;
            M2_AXI4_BVALID <= 1'b0;
            M2_AXI4_BRESP <= 2'b00;
            write_count <= 8'h0;
            dram_data_oe <= 1'b0;
            dram_cs <= 1'b1;
            dram_we <= 1'b1;
            dram_ras <= 1'b1;
            dram_cas <= 1'b1;
            dram_addr <= 14'h0; // Initialize dram_addr
            dram_ba <= 3'h0;   // Initialize dram_ba
        end else begin
            case (write_state)
                IDLE: begin
                    M2_AXI4_AWREADY <= 1'b1;
                    dram_cs <= 1'b1;
                    dram_data_oe <= 1'b0;
                    if (M2_AXI4_AWVALID && M2_AXI4_AWREADY) begin
                        write_id <= M2_AXI4_AWID;
                        write_addr <= M2_AXI4_AWADDR;
                        write_len <= M2_AXI4_AWLEN;
                        write_count <= 8'h0;
                        write_state <= DATA_PHASE;
                        M2_AXI4_AWREADY <= 1'b0;
                        M2_AXI4_WREADY <= 1'b1;
                    end
                end
                
                DATA_PHASE: begin
                    if (M2_AXI4_WVALID && M2_AXI4_WREADY) begin
                        // Convert to DRAM signals - ensure write happens
                        dram_cs <= 1'b0;
                        dram_we <= 1'b0;
                        dram_ras <= 1'b0;
                        dram_cas <= 1'b0;
                        // Simple address mapping: word address directly
                        dram_addr <= {6'b000000, write_addr[9:2]};  // Word address (divide by 4)
                        dram_ba <= 3'b000;     // Use bank 0 for simplicity
                        dram_data_out <= M2_AXI4_WDATA;
                        dram_data_oe <= 1'b1;
                        dram_dm <= ~M2_AXI4_WSTRB;
                        
                        write_count <= write_count + 1;
                        write_addr <= write_addr + 4;
                        
                        if (M2_AXI4_WLAST) begin
                            write_state <= RESP_PHASE;
                            M2_AXI4_WREADY <= 1'b0;
                        end
                    end
                end
                
                RESP_PHASE: begin
                    // Keep write signals active for one more cycle to ensure write completes
                    dram_cs <= 1'b1;
                    dram_data_oe <= 1'b0;
                    dram_we <= 1'b1;
                    M2_AXI4_BID <= write_id;
                    M2_AXI4_BRESP <= 2'b00; // OKAY
                    M2_AXI4_BVALID <= 1'b1;
                    
                    if (M2_AXI4_BREADY && M2_AXI4_BVALID) begin
                        M2_AXI4_BVALID <= 1'b0;
                        write_state <= IDLE;
                    end
                end
            endcase
        end
    end
    
    // Read channel state machine
    always @(posedge clk or negedge rst_n) begin
        if (!rst_n) begin
            read_state <= IDLE;
            M2_AXI4_ARREADY <= 1'b0;
            M2_AXI4_RVALID <= 1'b0;
            M2_AXI4_RRESP <= 2'b00;
            M2_AXI4_RLAST <= 1'b0;
            read_count <= 8'h0;
            read_data_valid <= 1'b0;
        end else begin
            case (read_state)
                IDLE: begin
                    M2_AXI4_ARREADY <= 1'b1;
                    M2_AXI4_RVALID <= 1'b0;
                    if (M2_AXI4_ARVALID && M2_AXI4_ARREADY) begin
                        read_id <= M2_AXI4_ARID;
                        read_addr <= M2_AXI4_ARADDR;
                        read_len <= M2_AXI4_ARLEN;
                        read_count <= 8'h0;
                        read_state <= ADDR_PHASE;
                        M2_AXI4_ARREADY <= 1'b0;
                    end
                end
                
                ADDR_PHASE: begin
                    // Issue read command to DRAM
                    dram_cs <= 1'b0;
                    dram_we <= 1'b1;
                    dram_ras <= 1'b0;
                    dram_cas <= 1'b0;
                    // Simple address mapping: word address directly
                    dram_addr <= {6'b000000, read_addr[9:2]};   // Word address (divide by 4)
                    dram_ba <= 3'b000;     // Use bank 0 for simplicity
                    dram_data_oe <= 1'b0;  // Ensure we're not driving the bus
                    read_state <= DATA_PHASE;
                end
                
                DATA_PHASE: begin
                    // Wait for DRAM data to be available
                    if (!read_data_valid) begin
                        read_data_reg <= dram_dq;
                        read_data_valid <= 1'b1;
                        dram_cs <= 1'b1; // Deassert chip select
                    end else begin
                        M2_AXI4_RID <= read_id;
                        M2_AXI4_RDATA <= read_data_reg;
                        M2_AXI4_RRESP <= 2'b00; // OKAY
                        M2_AXI4_RVALID <= 1'b1;
                        M2_AXI4_RLAST <= (read_count == read_len);
                        
                        if (M2_AXI4_RREADY && M2_AXI4_RVALID) begin
                            read_count <= read_count + 1;
                            read_addr <= read_addr + 4;
                            read_data_valid <= 1'b0;
                            
                            if (M2_AXI4_RLAST) begin
                                read_state <= IDLE;
                                M2_AXI4_RVALID <= 1'b0;
                                M2_AXI4_RLAST <= 1'b0;
                            end else begin
                                read_state <= ADDR_PHASE;
                            end
                        end
                    end
                end
            endcase
        end
    end
    
    // Clock generation for DRAM
    always @(posedge clk or negedge rst_n) begin
        if (!rst_n) begin
            dram_ck <= 1'b0;
        end else begin
            dram_ck <= ~dram_ck;
        end
    end


endmodule

TOP-SoC/sandbox/SoC-32bit/testbench_dram/tb_dram_controller.v
`timescale 1ns/1ps

`include "dram_controller.v"
`include "lpddr4_dummy.v"

module tb_dram_controller;
    parameter AXI4_ID_WIDTH = 4;
    parameter ADDR_WIDTH = 32;
    parameter DATA_WIDTH = 32;
    
    // Clock and reset
    reg clk;
    reg rst_n;
    
    // AXI4 signals
    reg  [AXI4_ID_WIDTH-1:0] M2_AXI4_AWID;
    reg  [ADDR_WIDTH-1:0]    M2_AXI4_AWADDR;
    reg  [7:0]               M2_AXI4_AWLEN;
    reg  [2:0]               M2_AXI4_AWSIZE;
    reg  [1:0]               M2_AXI4_AWBURST;
    reg                      M2_AXI4_AWVALID;
    wire                     M2_AXI4_AWREADY;
    
    reg  [DATA_WIDTH-1:0]    M2_AXI4_WDATA;
    reg  [(DATA_WIDTH/8)-1:0] M2_AXI4_WSTRB;
    reg                      M2_AXI4_WLAST;
    reg                      M2_AXI4_WVALID;
    wire                     M2_AXI4_WREADY;
    
    wire [AXI4_ID_WIDTH-1:0] M2_AXI4_BID;
    wire [1:0]               M2_AXI4_BRESP;
    wire                     M2_AXI4_BVALID;
    reg                      M2_AXI4_BREADY;
    
    reg  [AXI4_ID_WIDTH-1:0] M2_AXI4_ARID;
    reg  [ADDR_WIDTH-1:0]    M2_AXI4_ARADDR;
    reg  [7:0]               M2_AXI4_ARLEN;
    reg  [2:0]               M2_AXI4_ARSIZE;
    reg  [1:0]               M2_AXI4_ARBURST;
    reg                      M2_AXI4_ARVALID;
    wire                     M2_AXI4_ARREADY;
    
    wire [AXI4_ID_WIDTH-1:0] M2_AXI4_RID;
    wire [DATA_WIDTH-1:0]    M2_AXI4_RDATA;
    wire [1:0]               M2_AXI4_RRESP;
    wire                     M2_AXI4_RLAST;
    wire                     M2_AXI4_RVALID;
    reg                      M2_AXI4_RREADY;
    
    // DRAM interface
    wire dram_ck;
    wire dram_cs;
    wire dram_we;
    wire dram_ras;
    wire dram_cas;
    wire [13:0] dram_addr;
    wire [2:0] dram_ba;
    wire [31:0] dram_dq;
    wire [3:0] dram_dm;
    wire dram_dqs;
    
    // Instantiate DUT
    dram_controller #(
        .AXI4_ID_WIDTH(AXI4_ID_WIDTH),
        .ADDR_WIDTH(ADDR_WIDTH),
        .DATA_WIDTH(DATA_WIDTH)
    ) dut (
        .clk(clk),
        .rst_n(rst_n),
        .M2_AXI4_AWID(M2_AXI4_AWID),
        .M2_AXI4_AWADDR(M2_AXI4_AWADDR),
        .M2_AXI4_AWLEN(M2_AXI4_AWLEN),
        .M2_AXI4_AWSIZE(M2_AXI4_AWSIZE),
        .M2_AXI4_AWBURST(M2_AXI4_AWBURST),
        .M2_AXI4_AWVALID(M2_AXI4_AWVALID),
        .M2_AXI4_AWREADY(M2_AXI4_AWREADY),
        .M2_AXI4_WDATA(M2_AXI4_WDATA),
        .M2_AXI4_WSTRB(M2_AXI4_WSTRB),
        .M2_AXI4_WLAST(M2_AXI4_WLAST),
        .M2_AXI4_WVALID(M2_AXI4_WVALID),
        .M2_AXI4_WREADY(M2_AXI4_WREADY),
        .M2_AXI4_BID(M2_AXI4_BID),
        .M2_AXI4_BRESP(M2_AXI4_BRESP),
        .M2_AXI4_BVALID(M2_AXI4_BVALID),
        .M2_AXI4_BREADY(M2_AXI4_BREADY),
        .M2_AXI4_ARID(M2_AXI4_ARID),
        .M2_AXI4_ARADDR(M2_AXI4_ARADDR),
        .M2_AXI4_ARLEN(M2_AXI4_ARLEN),
        .M2_AXI4_ARSIZE(M2_AXI4_ARSIZE),
        .M2_AXI4_ARBURST(M2_AXI4_ARBURST),
        .M2_AXI4_ARVALID(M2_AXI4_ARVALID),
        .M2_AXI4_ARREADY(M2_AXI4_ARREADY),
        .M2_AXI4_RID(M2_AXI4_RID),
        .M2_AXI4_RDATA(M2_AXI4_RDATA),
        .M2_AXI4_RRESP(M2_AXI4_RRESP),
        .M2_AXI4_RLAST(M2_AXI4_RLAST),
        .M2_AXI4_RVALID(M2_AXI4_RVALID),
        .M2_AXI4_RREADY(M2_AXI4_RREADY),
        .dram_ck(dram_ck),
        .dram_cs(dram_cs),
        .dram_we(dram_we),
        .dram_ras(dram_ras),
        .dram_cas(dram_cas),
        .dram_addr(dram_addr),
        .dram_ba(dram_ba),
        .dram_dq(dram_dq),
        .dram_dm(dram_dm),
        .dram_dqs(dram_dqs)
    );
    
    // Instantiate LPDDR4 dummy
    lpddr4_dummy lpddr4_inst (
        .clk(dram_ck),
        .cs(dram_cs),
        .we(dram_we),
        .ras(dram_ras),
        .cas(dram_cas),
        .addr(dram_addr),
        .ba(dram_ba),
        .dq(dram_dq),
        .dm(dram_dm),
        .dqs(dram_dqs)
    );
    
    // Clock generation
    always #5 clk = ~clk;
    
    // Test tasks
    task axi_read;
        input [ADDR_WIDTH-1:0] addr;
        input [AXI4_ID_WIDTH-1:0] id;
        begin
            @(posedge clk);
            M2_AXI4_ARID = id;
            M2_AXI4_ARADDR = addr;
            M2_AXI4_ARLEN = 8'h0;
            M2_AXI4_ARSIZE = 3'b010;
            M2_AXI4_ARBURST = 2'b01;
            M2_AXI4_ARVALID = 1'b1;
            M2_AXI4_RREADY = 1'b1;
            
            wait(M2_AXI4_ARREADY == 1'b1);
            @(posedge clk);
            M2_AXI4_ARVALID = 1'b0;
            
            wait(M2_AXI4_RVALID == 1'b1);
            @(posedge clk);
            $display("Read: addr=%h data=%h", addr, M2_AXI4_RDATA);
            
            @(posedge clk);
            M2_AXI4_RREADY = 1'b0;
        end
    endtask
    
    task axi_write;
        input [ADDR_WIDTH-1:0] addr;
        input [DATA_WIDTH-1:0] data;
        input [AXI4_ID_WIDTH-1:0] id;
        begin
            @(posedge clk);
            M2_AXI4_AWID = id;
            M2_AXI4_AWADDR = addr;
            M2_AXI4_AWLEN = 8'h0;
            M2_AXI4_AWSIZE = 3'b010;
            M2_AXI4_AWBURST = 2'b01;
            M2_AXI4_AWVALID = 1'b1;
            
            wait(M2_AXI4_AWREADY == 1'b1);
            @(posedge clk);
            M2_AXI4_AWVALID = 1'b0;
            M2_AXI4_WDATA = data;
            M2_AXI4_WSTRB = 4'hF;
            M2_AXI4_WLAST = 1'b1;
            M2_AXI4_WVALID = 1'b1;
            M2_AXI4_BREADY = 1'b1;
            
            wait(M2_AXI4_WREADY == 1'b1);
            @(posedge clk);
            M2_AXI4_WVALID = 1'b0;
            M2_AXI4_WLAST = 1'b0;
            
            wait(M2_AXI4_BVALID == 1'b1);
            @(posedge clk);
            $display("Write: addr=%h data=%h resp=%h", addr, data, M2_AXI4_BRESP);
            
            @(posedge clk);
            M2_AXI4_BREADY = 1'b0;
        end
    endtask
    
    // Test stimulus
    initial begin
        // Initialize
        clk = 0;
        rst_n = 0;
        M2_AXI4_AWVALID = 0;
        M2_AXI4_WVALID = 0;
        M2_AXI4_BREADY = 0;
        M2_AXI4_ARVALID = 0;
        M2_AXI4_RREADY = 0;
        
        // Reset
        #20 rst_n = 1;
        #10;
        
        $display("Starting DRAM Controller Test...");
        
        // Test read from initial data - read each location to verify correct addressing
        $display("\n--- Testing Initial Data Read ---");
        axi_read(32'h00000000, 4'h1); // Should read 00000000
        axi_read(32'h00000004, 4'h2); // Should read 11111111
        axi_read(32'h00000008, 4'h3); // Should read 22222222
        axi_read(32'h0000000C, 4'h4); // Should read 33333333
        axi_read(32'h00000010, 4'h5); // Should read 44444444
        axi_read(32'h00000014, 4'h6); // Should read 55555555
        
        // Test write and read back - verify we can write to specific addresses
        $display("\n--- Testing Write and Read Back ---");
        axi_write(32'h00000020, 32'hDEADBEEF, 4'h7);
        #20; // Add delay to ensure write completes
        axi_read(32'h00000020, 4'h8); // Should read DEADBEEF
        
        axi_write(32'h00000024, 32'hCAFEBABE, 4'h9);
        #20; // Add delay to ensure write completes
        axi_read(32'h00000024, 4'hA); // Should read CAFEBABE
        
        // Additional test: verify written data persists
        $display("\n--- Verifying Data Persistence ---");
        axi_read(32'h00000020, 4'hB); // Should read DEADBEEF again
        axi_read(32'h00000024, 4'hC); // Should read CAFEBABE again
        
        #100;
        $display("\nTest completed!");
        $finish;
    end
    
    // Monitor
    initial begin
        $dumpfile("tb_dram_controller.vcd");
        $dumpvars(0, tb_dram_controller);
    end

endmodule

TOP-SoC/sandbox/SoC-32bit/testbench_dram2/tb_dram_controller.vcd
$date
	Wed Jun 11 08:53:13 2025
$end
$version
	Icarus Verilog
$end
$timescale
	1ps
$end
$scope module tb_dram_controller $end
$var wire 32 ! dram_dq [31:0] $end
$var wire 1 " dram_we $end
$var wire 1 # dram_ras $end
$var wire 1 $ dram_dqs $end
$var wire 4 % dram_dm [3:0] $end
$var wire 1 & dram_cs $end
$var wire 1 ' dram_ck $end
$var wire 1 ( dram_cas $end
$var wire 3 ) dram_ba [2:0] $end
$var wire 14 * dram_addr [13:0] $end
$var wire 1 + M2_AXI4_WREADY $end
$var wire 1 , M2_AXI4_RVALID $end
$var wire 2 - M2_AXI4_RRESP [1:0] $end
$var wire 1 . M2_AXI4_RLAST $end
$var wire 4 / M2_AXI4_RID [3:0] $end
$var wire 32 0 M2_AXI4_RDATA [31:0] $end
$var wire 1 1 M2_AXI4_BVALID $end
$var wire 2 2 M2_AXI4_BRESP [1:0] $end
$var wire 4 3 M2_AXI4_BID [3:0] $end
$var wire 1 4 M2_AXI4_AWREADY $end
$var wire 1 5 M2_AXI4_ARREADY $end
$var parameter 32 6 ADDR_WIDTH $end
$var parameter 32 7 AXI4_ID_WIDTH $end
$var parameter 32 8 DATA_WIDTH $end
$var reg 32 9 M2_AXI4_ARADDR [31:0] $end
$var reg 2 : M2_AXI4_ARBURST [1:0] $end
$var reg 4 ; M2_AXI4_ARID [3:0] $end
$var reg 8 < M2_AXI4_ARLEN [7:0] $end
$var reg 3 = M2_AXI4_ARSIZE [2:0] $end
$var reg 1 > M2_AXI4_ARVALID $end
$var reg 32 ? M2_AXI4_AWADDR [31:0] $end
$var reg 2 @ M2_AXI4_AWBURST [1:0] $end
$var reg 4 A M2_AXI4_AWID [3:0] $end
$var reg 8 B M2_AXI4_AWLEN [7:0] $end
$var reg 3 C M2_AXI4_AWSIZE [2:0] $end
$var reg 1 D M2_AXI4_AWVALID $end
$var reg 1 E M2_AXI4_BREADY $end
$var reg 1 F M2_AXI4_RREADY $end
$var reg 32 G M2_AXI4_WDATA [31:0] $end
$var reg 1 H M2_AXI4_WLAST $end
$var reg 4 I M2_AXI4_WSTRB [3:0] $end
$var reg 1 J M2_AXI4_WVALID $end
$var reg 1 K clk $end
$var reg 1 L rst_n $end
$scope module dut $end
$var wire 32 M M2_AXI4_ARADDR [31:0] $end
$var wire 2 N M2_AXI4_ARBURST [1:0] $end
$var wire 4 O M2_AXI4_ARID [3:0] $end
$var wire 8 P M2_AXI4_ARLEN [7:0] $end
$var wire 3 Q M2_AXI4_ARSIZE [2:0] $end
$var wire 1 > M2_AXI4_ARVALID $end
$var wire 32 R M2_AXI4_AWADDR [31:0] $end
$var wire 2 S M2_AXI4_AWBURST [1:0] $end
$var wire 4 T M2_AXI4_AWID [3:0] $end
$var wire 8 U M2_AXI4_AWLEN [7:0] $end
$var wire 3 V M2_AXI4_AWSIZE [2:0] $end
$var wire 1 D M2_AXI4_AWVALID $end
$var wire 1 E M2_AXI4_BREADY $end
$var wire 1 F M2_AXI4_RREADY $end
$var wire 32 W M2_AXI4_WDATA [31:0] $end
$var wire 1 H M2_AXI4_WLAST $end
$var wire 4 X M2_AXI4_WSTRB [3:0] $end
$var wire 1 J M2_AXI4_WVALID $end
$var wire 1 K clk $end
$var wire 32 Y dram_dq [31:0] $end
$var wire 1 L rst_n $end
$var parameter 2 Z ADDR_PHASE $end
$var parameter 32 [ ADDR_WIDTH $end
$var parameter 32 \ AXI4_ID_WIDTH $end
$var parameter 2 ] DATA_PHASE $end
$var parameter 32 ^ DATA_WIDTH $end
$var parameter 2 _ IDLE $end
$var parameter 2 ` RESP_PHASE $end
$var reg 1 5 M2_AXI4_ARREADY $end
$var reg 1 4 M2_AXI4_AWREADY $end
$var reg 4 a M2_AXI4_BID [3:0] $end
$var reg 2 b M2_AXI4_BRESP [1:0] $end
$var reg 1 1 M2_AXI4_BVALID $end
$var reg 32 c M2_AXI4_RDATA [31:0] $end
$var reg 4 d M2_AXI4_RID [3:0] $end
$var reg 1 . M2_AXI4_RLAST $end
$var reg 2 e M2_AXI4_RRESP [1:0] $end
$var reg 1 , M2_AXI4_RVALID $end
$var reg 1 + M2_AXI4_WREADY $end
$var reg 14 f dram_addr [13:0] $end
$var reg 3 g dram_ba [2:0] $end
$var reg 1 ( dram_cas $end
$var reg 1 ' dram_ck $end
$var reg 1 & dram_cs $end
$var reg 1 h dram_data_oe $end
$var reg 32 i dram_data_out [31:0] $end
$var reg 4 j dram_dm [3:0] $end
$var reg 1 $ dram_dqs $end
$var reg 1 # dram_ras $end
$var reg 1 " dram_we $end
$var reg 32 k read_addr [31:0] $end
$var reg 8 l read_count [7:0] $end
$var reg 32 m read_data_reg [31:0] $end
$var reg 1 n read_data_valid $end
$var reg 4 o read_id [3:0] $end
$var reg 8 p read_len [7:0] $end
$var reg 2 q read_state [1:0] $end
$var reg 32 r write_addr [31:0] $end
$var reg 8 s write_count [7:0] $end
$var reg 4 t write_id [3:0] $end
$var reg 8 u write_len [7:0] $end
$var reg 2 v write_state [1:0] $end
$upscope $end
$scope module lpddr4_inst $end
$var wire 14 w addr [13:0] $end
$var wire 3 x ba [2:0] $end
$var wire 1 ( cas $end
$var wire 1 ' clk $end
$var wire 1 & cs $end
$var wire 4 y dm [3:0] $end
$var wire 32 z dq [31:0] $end
$var wire 1 $ dqs $end
$var wire 1 # ras $end
$var wire 1 " we $end
$var wire 12 { word_addr [11:0] $end
$var wire 12 | mem_addr [11:0] $end
$var reg 32 } data_out [31:0] $end
$var reg 1 ~ output_enable $end
$upscope $end
$scope task axi_read $end
$var reg 32 !" addr [31:0] $end
$var reg 4 "" id [3:0] $end
$upscope $end
$scope task axi_write $end
$var reg 32 #" addr [31:0] $end
$var reg 32 $" data [31:0] $end
$var reg 4 %" id [3:0] $end
$upscope $end
$upscope $end
$enddefinitions $end
$comment Show the parameter values. $end
$dumpall
b11 `
b0 _
b100000 ^
b10 ]
b100 \
b100000 [
b1 Z
b100000 8
b100 7
b100000 6
$end
#0
$dumpvars
bx %"
bx $"
bx #"
bx ""
bx !"
0~
b0 }
b0 |
b0 {
bz z
bx y
b0 x
b0 w
b0 v
bx u
bx t
b0 s
bx r
b0 q
bx p
bx o
0n
bx m
b0 l
bx k
bx j
bx i
0h
b0 g
b0 f
b0 e
bx d
bx c
b0 b
bx a
bz Y
bx X
bx W
bx V
bx U
bx T
bx S
bx R
bx Q
bx P
bx O
bx N
bx M
0L
0K
0J
bx I
xH
bx G
0F
0E
0D
bx C
bx B
bx A
bx @
bx ?
0>
bx =
bx <
bx ;
bx :
bx 9
05
04
bx 3
b0 2
01
bx 0
bx /
0.
b0 -
0,
0+
b0 *
b0 )
1(
0'
1&
bx %
x$
1#
1"
bz !
$end
#5000
1K
#10000
0K
#15000
1K
#20000
0K
1L
#25000
1'
15
14
1K
#30000
0K
b1 ""
b0 !"
#35000
05
b1 q
b0 p
b0 k
b1 o
0'
1F
1>
b1 :
b1 N
b10 =
b10 Q
b0 <
b0 P
b0 9
b0 M
b1 ;
b1 O
1K
#40000
0K
#45000
b0 !
b0 Y
b0 z
1~
1'
b10 q
0(
0#
0&
0>
1K
#50000
0K
#55000
1&
1n
b0 m
0'
1K
#60000
0K
#65000
bz !
bz Y
bz z
0~
1'
1.
1,
b0 0
b0 c
b1 /
b1 d
1K
#70000
0K
#75000
0.
0,
b0 q
0n
b100 k
b1 l
0'
1K
#80000
0K
#85000
1'
15
b10 ""
b100 !"
0F
1K
#90000
0K
#95000
05
b1 q
b0 l
b10 o
0'
1F
1>
b100 9
b100 M
b10 ;
b10 O
1K
#100000
0K
#105000
b0 !
b0 Y
b0 z
1~
1'
b10 q
b1 *
b1 f
b1 w
0&
0>
1K
#110000
0K
#115000
1&
1n
0'
1K
#120000
0K
#125000
bz !
bz Y
bz z
0~
1'
1.
1,
b10 /
b10 d
1K
#130000
0K
#135000
0.
0,
b0 q
0n
b1000 k
b1 l
0'
1K
#140000
0K
#145000
1'
15
b11 ""
b1000 !"
0F
1K
#150000
0K
#155000
05
b1 q
b0 l
b11 o
0'
1F
1>
b1000 9
b1000 M
b11 ;
b11 O
1K
#160000
0K
#165000
b0 !
b0 Y
b0 z
1~
1'
b10 q
b10 *
b10 f
b10 w
0&
0>
1K
#170000
0K
#175000
1&
1n
0'
1K
#180000
0K
#185000
bz !
bz Y
bz z
0~
1'
1.
1,
b11 /
b11 d
1K
#190000
0K
#195000
0.
0,
b0 q
0n
b1100 k
b1 l
0'
1K
#200000
0K
#205000
1'
15
b100 ""
b1100 !"
0F
1K
#210000
0K
#215000
05
b1 q
b0 l
b100 o
0'
1F
1>
b1100 9
b1100 M
b100 ;
b100 O
1K
#220000
0K
#225000
b0 !
b0 Y
b0 z
1~
1'
b10 q
b11 *
b11 f
b11 w
0&
0>
1K
#230000
0K
#235000
1&
1n
0'
1K
#240000
0K
#245000
bz !
bz Y
bz z
0~
1'
1.
1,
b100 /
b100 d
1K
#250000
0K
#255000
0.
0,
b0 q
0n
b10000 k
b1 l
0'
1K
#260000
0K
#265000
1'
15
b101 ""
b10000 !"
0F
1K
#270000
0K
#275000
05
b1 q
b0 l
b101 o
0'
1F
1>
b10000 9
b10000 M
b101 ;
b101 O
1K
#280000
0K
#285000
b0 !
b0 Y
b0 z
1~
b1 |
b1 {
1'
b10 q
b100 *
b100 f
b100 w
0&
0>
1K
#290000
0K
#295000
1&
1n
0'
1K
#300000
0K
#305000
bz !
bz Y
bz z
0~
1'
1.
1,
b101 /
b101 d
1K
#310000
0K
#315000
0.
0,
b0 q
0n
b10100 k
b1 l
0'
1K
#320000
0K
#325000
1'
15
b110 ""
b10100 !"
0F
1K
#330000
0K
#335000
05
b1 q
b0 l
b110 o
0'
1F
1>
b10100 9
b10100 M
b110 ;
b110 O
1K
#340000
0K
#345000
b10001000100010001000100010001 !
b10001000100010001000100010001 Y
b10001000100010001000100010001 z
1~
b10001000100010001000100010001 }
1'
b10 q
b101 *
b101 f
b101 w
0&
0>
1K
#350000
0K
#355000
1&
1n
b10001000100010001000100010001 m
0'
1K
#360000
0K
#365000
bz !
bz Y
bz z
0~
1'
1.
1,
b10001000100010001000100010001 0
b10001000100010001000100010001 c
b110 /
b110 d
1K
#370000
0K
#375000
0.
0,
b0 q
0n
b11000 k
b1 l
0'
1K
#380000
0K
#385000
1'
15
b111 %"
b11011110101011011011111011101111 $"
b100000 #"
0F
1K
#390000
0K
#395000
1+
04
b10 v
b0 u
b100000 r
b111 t
0'
1D
b1 @
b1 S
b10 C
b10 V
b0 B
b0 U
b100000 ?
b100000 R
b111 A
b111 T
1K
#400000
0K
#405000
b10 |
b11011110101011011011111011101111 !
b11011110101011011011111011101111 Y
b11011110101011011011111011101111 z
b10 {
1'
0+
b11 v
b100100 r
b1 s
b0 %
b0 j
b0 y
1h
b11011110101011011011111011101111 i
b1000 *
b1000 f
b1000 w
0"
0&
1E
1J
1H
b1111 I
b1111 X
b11011110101011011011111011101111 G
b11011110101011011011111011101111 W
0D
1K
#410000
0K
#415000
bz !
bz Y
bz z
11
b111 3
b111 a
1"
0h
1&
0'
0H
0J
1K
#420000
0K
#425000
1'
b0 v
01
1K
#430000
0K
#435000
14
0'
0E
1K
#440000
0K
#445000
1'
1K
#450000
0K
