TPU/src/systolic.v
// Module: systolic array for matrix multiplication (32x32) 
// Author: Ahmed Abdelazeem
// Email: a.abdelazeem201@gmail.com
// Thanks to Ahmed Abdelazeen for the design! Much appreciated!
//
// Description:
// This module implements a 32x32 systolic array for matrix multiplication with input for 64-bit
// The array performs matrix multiplications using weights and data buffers. 
// The weight and data queues are shifted as needed, and multiplication results are stored in 
// a matrix that can be accessed through the `mul_outcome` output.

module systolic #(
    parameter ARRAY_SIZE = 32,             // Size of the array (32x32)
    parameter SRAM_DATA_WIDTH = 64,        // Data width for SRAM input
    parameter DATA_WIDTH = 8               // Data width for elements in the matrix
)(
    input wire clk,                             // Clock signal
    input wire rst_n,                           // Synchronous reset (active low)
    input wire alu_start,                       // Enable signal to start computation
    input wire  [8:0] cycle_num,                 // Current cycle number
    input wire  [SRAM_DATA_WIDTH-1:0] sram_rdata_w0, // SRAM input for weight queue (64-bit)
    input wire  [SRAM_DATA_WIDTH-1:0] sram_rdata_w1, 
    input wire  [SRAM_DATA_WIDTH-1:0] sram_rdata_w2, 
    input wire  [SRAM_DATA_WIDTH-1:0] sram_rdata_w3,  
    input wire  [SRAM_DATA_WIDTH-1:0] sram_rdata_d0, // SRAM input for data queue (64-bit)
    input wire  [SRAM_DATA_WIDTH-1:0] sram_rdata_d1, 
    input wire  [SRAM_DATA_WIDTH-1:0] sram_rdata_d2, 
    input wire  [SRAM_DATA_WIDTH-1:0] sram_rdata_d3, 
    input wire  [5:0] matrix_index,              // Index for selecting output matrix
    output reg signed [(ARRAY_SIZE*(DATA_WIDTH+DATA_WIDTH+5))-1:0] mul_outcome // Output of the multiplication result
);

// Local parameters for controlling matrix multiplication flow
localparam FIRST_OUT = 33;
localparam PARALLEL_START = 65;
localparam OUTCOME_WIDTH = DATA_WIDTH + DATA_WIDTH + 5; // Result width of multiplication

// Internal registers
reg signed [OUTCOME_WIDTH-1:0] matrix_mul_2D [0:ARRAY_SIZE-1][0:ARRAY_SIZE-1]; // Matrix to hold multiplication results
reg signed [OUTCOME_WIDTH-1:0] matrix_mul_2D_nx [0:ARRAY_SIZE-1][0:ARRAY_SIZE-1]; // Next state of matrix_mul_2D
reg signed [DATA_WIDTH-1:0] data_queue [0:ARRAY_SIZE-1][0:ARRAY_SIZE-1];         // Data queue for inputs
reg signed [DATA_WIDTH-1:0] weight_queue [0:ARRAY_SIZE-1][0:ARRAY_SIZE-1];       // Weight queue for inputs
reg signed [DATA_WIDTH+DATA_WIDTH-1:0] mul_result;  // Temporary variable for holding multiplication result

reg [5:0] upper_bound, lower_bound; // Variables for matrix indexing
integer i, j;                        // Loop indices for iteration

// Shift weight and data queues
always @(posedge clk) begin
    if (~rst_n) begin // On reset, initialize the queues to 0
        for (i = 0; i < ARRAY_SIZE; i = i + 1) begin
            for (j = 0; j < ARRAY_SIZE; j = j + 1) begin
                weight_queue[i][j] <= 0;
                data_queue[i][j] <= 0;
            end
        end
    end
    else if (alu_start) begin
        // Shift weight queue
        for (i = 0; i < 8; i = i + 1) begin
            weight_queue[0][i] <= sram_rdata_w0[63-8*i-:8];
            weight_queue[0][i+8] <= sram_rdata_w1[63-8*i-:8];
            weight_queue[0][i+16] <= sram_rdata_w2[63-8*i-:8];
            weight_queue[0][i+24] <= sram_rdata_w3[63-8*i-:8];
        end
        for (i = 1; i < ARRAY_SIZE; i = i + 1)
            for (j = 0; j < ARRAY_SIZE; j = j + 1)
                weight_queue[i][j] <= weight_queue[i-1][j];
                
        // Shift data queue
        for (i = 0; i < 8; i = i + 1) begin
            data_queue[i][0] <= sram_rdata_d0[63-8*i-:8];
            data_queue[i+8][0] <= sram_rdata_d1[63-8*i-:8];
            data_queue[i+16][0] <= sram_rdata_d2[63-8*i-:8];
            data_queue[i+24][0] <= sram_rdata_d3[63-8*i-:8];
        end
        for (i = 0; i < ARRAY_SIZE; i = i + 1)
            for (j = 1; j < ARRAY_SIZE; j = j + 1)
                data_queue[i][j] <= data_queue[i][j-1];
    end
end

// Multiplication unit
always @(posedge clk) begin
    if (~rst_n) begin // Reset the matrix multiplication results to 0
        for (i = 0; i < ARRAY_SIZE; i = i + 1) 
            for (j = 0; j < ARRAY_SIZE; j = j + 1)
                matrix_mul_2D[i][j] <= 0;
    end
    else begin
        for (i = 0; i < ARRAY_SIZE; i = i + 1) 
            for (j = 0; j < ARRAY_SIZE; j = j + 1) 
                matrix_mul_2D[i][j] <= matrix_mul_2D_nx[i][j];
    end
end

// Combinational logic for multiplication and accumulation
always @(*) begin
    if (alu_start) begin
        for (i = 0; i < ARRAY_SIZE; i = i + 1) begin
            for (j = 0; j < ARRAY_SIZE; j = j + 1) begin
                if ((cycle_num >= FIRST_OUT && (i+j) == (cycle_num - FIRST_OUT) % 64) || 
                    (cycle_num >= PARALLEL_START && (i+j) == (cycle_num - PARALLEL_START) % 64)) begin
                    mul_result = weight_queue[i][j] * data_queue[i][j];
                    matrix_mul_2D_nx[i][j] = { {5{mul_result[15]}}, mul_result }; // Sign extension of the result
                end
                else if (cycle_num >= 1 && i + j <= (cycle_num - 1)) begin
                    mul_result = weight_queue[i][j] * data_queue[i][j];
                    matrix_mul_2D_nx[i][j] = matrix_mul_2D[i][j] + { {5{mul_result[15]}}, mul_result }; // Accumulate results
                end
                else begin
                    mul_result = 0;
                    matrix_mul_2D_nx[i][j] = matrix_mul_2D[i][j];
                end
            end
        end
    end
    else begin
        mul_result = 0;
        for (i = 0; i < ARRAY_SIZE; i = i + 1)
            for (j = 0; j < ARRAY_SIZE; j = j + 1)
                matrix_mul_2D_nx[i][j] = matrix_mul_2D[i][j];
    end
end

// Output generation: Fetch multiplication results indexed by matrix_index
always @(*) begin
    if (matrix_index < ARRAY_SIZE) begin
        upper_bound = matrix_index;
        lower_bound = matrix_index + ARRAY_SIZE;
    end
    else begin
        upper_bound = matrix_index - ARRAY_SIZE;
        lower_bound = matrix_index;
    end

    // Initialize the output
    for (i = 0; i < ARRAY_SIZE * OUTCOME_WIDTH; i = i + 1)
        mul_outcome[i] = 0;

    // Fetch data from the multiplication result matrix
    for (i = 0; i < ARRAY_SIZE; i = i + 1) begin
        for (j = 0; j < ARRAY_SIZE - i; j = j + 1) begin
            if (i + j == upper_bound)
                mul_outcome[i * OUTCOME_WIDTH +: OUTCOME_WIDTH] = matrix_mul_2D[i][j];
        end
    end

    for (i = 1; i < ARRAY_SIZE; i = i + 1) begin
        for (j = ARRAY_SIZE - i; j < ARRAY_SIZE; j = j + 1) begin
            if (i + j == lower_bound)
                mul_outcome[i * OUTCOME_WIDTH +: OUTCOME_WIDTH] = matrix_mul_2D[i][j];
        end
    end
end

endmodule

TPU/tb/tb_systolic.v
`timescale 1ns/1ps

module tb_systolic;

  // Parameters
  parameter ARRAY_SIZE = 32;
  parameter SRAM_DATA_WIDTH = 64;
  parameter DATA_WIDTH = 8;
  parameter OUTCOME_WIDTH = DATA_WIDTH + DATA_WIDTH + 5;

  // Inputs
  reg clk;
  reg rst_n;
  reg alu_start;
  reg [8:0] cycle_num;
  reg [SRAM_DATA_WIDTH-1:0] sram_rdata_w0, sram_rdata_w1, sram_rdata_w2, sram_rdata_w3;
  reg [SRAM_DATA_WIDTH-1:0] sram_rdata_d0, sram_rdata_d1, sram_rdata_d2, sram_rdata_d3;
  reg [5:0] matrix_index;

  // Output
  wire signed [(ARRAY_SIZE * OUTCOME_WIDTH) - 1:0] mul_outcome;

  // Instantiate the DUT
  systolic dut (
    .clk(clk),
    .rst_n(rst_n),
    .alu_start(alu_start),
    .cycle_num(cycle_num),
    .sram_rdata_w0(sram_rdata_w0),
    .sram_rdata_w1(sram_rdata_w1),
    .sram_rdata_w2(sram_rdata_w2),
    .sram_rdata_w3(sram_rdata_w3),
    .sram_rdata_d0(sram_rdata_d0),
    .sram_rdata_d1(sram_rdata_d1),
    .sram_rdata_d2(sram_rdata_d2),
    .sram_rdata_d3(sram_rdata_d3),
    .matrix_index(matrix_index),
    .mul_outcome(mul_outcome)
  );

  // Clock generation
  initial clk = 0;
  always #5 clk = ~clk; // 100MHz clock

  // Stimulus
  integer i;
  initial begin
    // VCD for GTKWave
    $dumpfile("systolic.vcd");
    $dumpvars(0, tb_systolic);
    
    // Initialize
    rst_n = 0;
    alu_start = 0;
    cycle_num = 0;
    matrix_index = 0;
    sram_rdata_w0 = 0;
    sram_rdata_w1 = 0;
    sram_rdata_w2 = 0;
    sram_rdata_w3 = 0;
    sram_rdata_d0 = 0;
    sram_rdata_d1 = 0;
    sram_rdata_d2 = 0;
    sram_rdata_d3 = 0;
    #20;

    rst_n = 1;
    alu_start = 1;

    // Apply test data for 10 cycles
    for (i = 0; i < 10; i = i + 1) begin
      // Use predictable test pattern: 8-bit ramp
      sram_rdata_w0 = {8{8'd1}};
      sram_rdata_w1 = {8{8'd1}};
      sram_rdata_w2 = {8{8'd1}};
      sram_rdata_w3 = {8{8'd1}};

      sram_rdata_d0 = {8{8'd1}};
      sram_rdata_d1 = {8{8'd1}};
      sram_rdata_d2 = {8{8'd1}};
      sram_rdata_d3 = {8{8'd1}};

      cycle_num = i;

      // Wait for 1 clock cycle
      #10;

      // Observe output after pipeline fill (about cycle 35 onward)
      if (i > 35) begin
        $display("Cycle %0d - mul_outcome: %h", i, mul_outcome);
      end
    end

    alu_start = 0;
    #20;

    $finish;
  end

endmodule

TPU/systolic.vcd
$date
	Fri May 16 13:08:49 2025
$end
$version
	Icarus Verilog
$end
$timescale
	1ps
$end
$scope module tb_systolic $end
$var wire 672 ! mul_outcome [671:0] $end
$var parameter 32 " ARRAY_SIZE $end
$var parameter 32 # DATA_WIDTH $end
$var parameter 34 $ OUTCOME_WIDTH $end
$var parameter 32 % SRAM_DATA_WIDTH $end
$var reg 1 & alu_start $end
$var reg 1 ' clk $end
$var reg 9 ( cycle_num [8:0] $end
$var reg 6 ) matrix_index [5:0] $end
$var reg 1 * rst_n $end
$var reg 64 + sram_rdata_d0 [63:0] $end
$var reg 64 , sram_rdata_d1 [63:0] $end
$var reg 64 - sram_rdata_d2 [63:0] $end
$var reg 64 . sram_rdata_d3 [63:0] $end
$var reg 64 / sram_rdata_w0 [63:0] $end
$var reg 64 0 sram_rdata_w1 [63:0] $end
$var reg 64 1 sram_rdata_w2 [63:0] $end
$var reg 64 2 sram_rdata_w3 [63:0] $end
$var integer 32 3 i [31:0] $end
$scope module dut $end
$var wire 1 & alu_start $end
$var wire 1 ' clk $end
$var wire 9 4 cycle_num [8:0] $end
$var wire 6 5 matrix_index [5:0] $end
$var wire 1 * rst_n $end
$var wire 64 6 sram_rdata_d0 [63:0] $end
$var wire 64 7 sram_rdata_d1 [63:0] $end
$var wire 64 8 sram_rdata_d2 [63:0] $end
$var wire 64 9 sram_rdata_d3 [63:0] $end
$var wire 64 : sram_rdata_w0 [63:0] $end
$var wire 64 ; sram_rdata_w1 [63:0] $end
$var wire 64 < sram_rdata_w2 [63:0] $end
$var wire 64 = sram_rdata_w3 [63:0] $end
$var parameter 32 > ARRAY_SIZE $end
$var parameter 32 ? DATA_WIDTH $end
$var parameter 32 @ FIRST_OUT $end
$var parameter 34 A OUTCOME_WIDTH $end
$var parameter 32 B PARALLEL_START $end
$var parameter 32 C SRAM_DATA_WIDTH $end
$var reg 6 D lower_bound [5:0] $end
$var reg 672 E mul_outcome [671:0] $end
$var reg 16 F mul_result [15:0] $end
$var reg 6 G upper_bound [5:0] $end
$var integer 32 H i [31:0] $end
$var integer 32 I j [31:0] $end
$upscope $end
$upscope $end
$enddefinitions $end
$comment Show the parameter values. $end
$dumpall
b1000000 C
b1000001 B
b10101 A
b100001 @
b1000 ?
b100000 >
b1000000 %
b10101 $
b1000 #
b100000 "
$end
#0
$dumpvars
b100000 I
b100000 H
b0 G
b0 F
bx E
b100000 D
b0 =
b0 <
b0 ;
b0 :
b0 9
b0 8
b0 7
b0 6
b0 5
b0 4
bx 3
b0 2
b0 1
b0 0
b0 /
b0 .
b0 -
b0 ,
b0 +
0*
b0 )
b0 (
0'
0&
bx !
$end
#5000
b0 !
b0 E
b100000 I
b100000 H
1'
#10000
0'
#15000
b100000 I
b100000 H
1'
#20000
b100000 I
b100000 H
0'
b100000001000000010000000100000001000000010000000100000001 .
b100000001000000010000000100000001000000010000000100000001 9
b100000001000000010000000100000001000000010000000100000001 -
b100000001000000010000000100000001000000010000000100000001 8
b100000001000000010000000100000001000000010000000100000001 ,
b100000001000000010000000100000001000000010000000100000001 7
b100000001000000010000000100000001000000010000000100000001 +
b100000001000000010000000100000001000000010000000100000001 6
b100000001000000010000000100000001000000010000000100000001 2
b100000001000000010000000100000001000000010000000100000001 =
b100000001000000010000000100000001000000010000000100000001 1
b100000001000000010000000100000001000000010000000100000001 <
b100000001000000010000000100000001000000010000000100000001 0
b100000001000000010000000100000001000000010000000100000001 ;
b100000001000000010000000100000001000000010000000100000001 /
b100000001000000010000000100000001000000010000000100000001 :
b0 3
1&
1*
#25000
b100000 I
b100000 H
1'
#30000
b0 F
b100000 I
b100000 H
0'
b1 (
b1 4
b1 3
#35000
b1 !
b1 E
b0 F
b100000 I
b100000 H
1'
#40000
b0 F
b100000 I
b100000 H
0'
b10 (
b10 4
b10 3
#45000
b10 !
b10 E
b0 F
b100000 I
b100000 H
1'
#50000
b0 F
b100000 I
b100000 H
0'
b11 (
b11 4
b11 3
#55000
b11 !
b11 E
b0 F
b100000 I
b100000 H
1'
#60000
b0 F
b100000 I
b100000 H
0'
b100 (
b100 4
b100 3
#65000
b100 !
b100 E
b0 F
b100000 I
b100000 H
1'
#70000
b0 F
b100000 I
b100000 H
0'
b101 (
b101 4
b101 3
#75000
b101 !
b101 E
b0 F
b100000 I
b100000 H
1'
#80000
b0 F
b100000 I
b100000 H
0'
b110 (
b110 4
b110 3
#85000
b110 !
b110 E
b0 F
b100000 I
b100000 H
1'
#90000
b0 F
b100000 I
b100000 H
0'
b111 (
b111 4
b111 3
#95000
b111 !
b111 E
b0 F
b100000 I
b100000 H
1'
#100000
b0 F
b100000 I
b100000 H
0'
b1000 (
b1000 4
b1000 3
#105000
b1000 !
b1000 E
b0 F
b100000 I
b100000 H
1'
#110000
b0 F
b100000 I
b100000 H
0'
b1001 (
b1001 4
b1001 3
#115000
b1001 !
b1001 E
b0 F
b100000 I
b100000 H
1'
#120000
b100000 I
b100000 H
0'
0&
b1010 3
#125000
b100000 I
b100000 H
1'
#130000
0'
#135000
b100000 I
b100000 H
1'
